{
  "harvest_metadata": {
    "harvester_version": "2.0",
    "last_harvest": "2025-06-18T16:52:42.827305",
    "total_sessions": 11,
    "total_videos": 1315,
    "unique_videos": 156,
    "total_time": 1142.2975800037384,
    "average_success_rate": 100.0,
    "total_score": 186099,
    "best_session_score": 42313
  },
  "sessions": [
    {
      "session_id": "harvest_20250618_143235",
      "timestamp": "2025-06-18T14:32:35.351923",
      "videos_found": 156,
      "success_rate": 98.71794871794873,
      "completion_time": 662.7756650447845,
      "target_filter": "harvest_batch_1",
      "total_score": 37100
    },
    {
      "session_id": "harvest_20250618_144454",
      "timestamp": "2025-06-18T14:44:54.487424",
      "videos_found": 156,
      "success_rate": 98.71794871794873,
      "completion_time": 678.1280870437622,
      "target_filter": "harvest_batch_2",
      "total_score": 42313
    },
    {
      "session_id": "harvest_20250618_145954",
      "timestamp": "2025-06-18T15:08:53.587926",
      "videos_found": 141,
      "success_rate": 99.29078014184397,
      "completion_time": 538.671817779541,
      "target_filter": "harvest_batch_1",
      "total_score": 3948,
      "continuation_point": {
        "strategy": "fresh_start",
        "reasoning": "Session 1: Fresh start from top",
        "scroll_offset": 0,
        "target_date_range": null,
        "anchor_video_id": null,
        "expected_scroll_depth": 0,
        "date_filter_active": false,
        "scroll_strategy": "standard"
      }
    },
    {
      "session_id": "harvest_20250618_151045",
      "timestamp": "2025-06-18T15:21:37.119793",
      "videos_found": 156,
      "success_rate": 98.71794871794873,
      "completion_time": 651.5123419761658,
      "target_filter": "harvest_batch_2",
      "total_score": 4228,
      "continuation_point": {
        "strategy": "scroll_offset",
        "reasoning": "Session 2: Start at scroll 14 to avoid overlap",
        "scroll_offset": 14,
        "target_date_range": null,
        "anchor_video_id": null,
        "expected_scroll_depth": 34,
        "date_filter_active": false,
        "scroll_strategy": "adaptive"
      }
    },
    {
      "session_id": "harvest_20250618_152257",
      "timestamp": "2025-06-18T15:33:19.757130",
      "videos_found": 20,
      "success_rate": 100.0,
      "completion_time": 622.5261981487274,
      "target_filter": "harvest_batch_3",
      "total_score": 3810,
      "continuation_point": {
        "strategy": "video_id_anchor",
        "reasoning": "Session 3: Continue from video 97792963... (8 years ago)",
        "scroll_offset": 24,
        "target_date_range": "8 years ago",
        "anchor_video_id": "1455977097792963",
        "expected_scroll_depth": 39,
        "date_filter_active": true,
        "scroll_strategy": "deep"
      }
    },
    {
      "session_id": "harvest_20250618_153639",
      "timestamp": "2025-06-18T15:46:26.395460",
      "videos_found": 147,
      "success_rate": 98.63945578231292,
      "completion_time": 586.5950629711151,
      "target_filter": "harvest_batch_1",
      "total_score": 4046,
      "continuation_point": {
        "strategy": "fresh_start",
        "reasoning": "Session 1: Fresh start from top",
        "scroll_offset": 0,
        "target_date_range": null,
        "anchor_video_id": null,
        "expected_scroll_depth": 0,
        "date_filter_active": false,
        "scroll_strategy": "standard"
      }
    },
    {
      "session_id": "harvest_20250618_162115",
      "timestamp": "2025-06-18T16:24:29.310398",
      "videos_found": 20,
      "success_rate": 80.0,
      "completion_time": 193.6878399848938,
      "target_filter": "harvest_batch_1",
      "total_score": 1358,
      "continuation_point": {
        "strategy": "fresh_start",
        "reasoning": "Session 1: Fresh start from top",
        "scroll_offset": 0,
        "target_date_range": null,
        "anchor_video_id": null,
        "expected_scroll_depth": 0,
        "date_filter_active": false,
        "scroll_strategy": "standard"
      }
    },
    {
      "session_id": "harvest_20250618_162929",
      "timestamp": "2025-06-18T16:29:40.225487",
      "videos_found": 0,
      "success_rate": 0,
      "completion_time": 10.867227792739868,
      "target_filter": "harvest_batch_2",
      "total_score": 0,
      "continuation_point": {
        "strategy": "scroll_offset",
        "reasoning": "Session 2: Start at scroll 15 to avoid overlap",
        "scroll_offset": 15,
        "target_date_range": null,
        "anchor_video_id": null,
        "expected_scroll_depth": 35,
        "date_filter_active": false,
        "scroll_strategy": "adaptive"
      }
    },
    {
      "session_id": "harvest_20250618_163340",
      "timestamp": "2025-06-18T16:37:17.178698",
      "videos_found": 20,
      "success_rate": 100.0,
      "completion_time": 216.6480541229248,
      "target_filter": "harvest_batch_1",
      "total_score": 1585,
      "continuation_point": {
        "strategy": "fresh_start",
        "reasoning": "Session 1: Fresh start from top",
        "scroll_offset": 0,
        "target_date_range": null,
        "anchor_video_id": null,
        "expected_scroll_depth": 0,
        "date_filter_active": false,
        "scroll_strategy": "standard"
      }
    },
    {
      "session_id": "harvest_20250618_164110",
      "timestamp": "2025-06-18T16:44:41.238400",
      "videos_found": 20,
      "success_rate": 100.0,
      "completion_time": 211.22795629501343,
      "target_filter": "harvest_batch_2",
      "total_score": 1610,
      "continuation_point": {
        "strategy": "scroll_offset",
        "reasoning": "Session 2: Start at scroll 10 to avoid overlap",
        "scroll_offset": 10,
        "target_date_range": null,
        "anchor_video_id": null,
        "expected_scroll_depth": 30,
        "date_filter_active": false,
        "scroll_strategy": "adaptive"
      }
    },
    {
      "session_id": "harvest_20250618_164618",
      "timestamp": "2025-06-18T16:52:42.824594",
      "videos_found": 20,
      "success_rate": 100.0,
      "completion_time": 384.5721209049225,
      "target_filter": "harvest_batch_3",
      "total_score": 2815,
      "continuation_point": {
        "strategy": "video_id_anchor",
        "reasoning": "Session 3: Continue from video 97792963... (8 years ago)",
        "scroll_offset": 24,
        "target_date_range": "8 years ago",
        "anchor_video_id": "1455977097792963",
        "expected_scroll_depth": 39,
        "date_filter_active": true,
        "scroll_strategy": "deep"
      }
    }
  ],
  "all_videos": {
    "595328265177242": {
      "video_id": "595328265177242",
      "title": "Draga mama 218. Nakon ljetne pauze",
      "url": "https://www.facebook.com/watch/?v=595328265177242",
      "date": "3 years ago",
      "date_raw": "3 years ago",
      "likes": 0,
      "comments": 0,
      "shares": 0,
      "views": "",
      "description": "",
      "thumbnail_url": ""
    },
    "330882645555959": {
      "video_id": "330882645555959",
      "title": "Draga mama 220. Moj drug Lipšo i ja",
      "url": "https://www.facebook.com/watch/?v=330882645555959",
      "date": "3 years ago",
      "date_raw": "3 years ago",
      "likes": 0,
      "comments": 0,
      "shares": 0,
      "views": "",
      "description": "",
      "thumbnail_url": ""
    },
    "712197699742053": {
      "video_id": "712197699742053",
      "title": "Draga mama 219. Probna pravna paradržava",
      "url": "https://www.facebook.com/watch/?v=712197699742053",
      "date": "3 years ago",
      "date_raw": "3 years ago",
      "likes": 0,
      "comments": 0,
      "shares": 0,
      "views": "",
      "description": "",
      "thumbnail_url": ""
    },
    "209334704509484": {
      "video_id": "209334704509484",
      "title": "Draga mama 218. \"Oni što ostaju i oni što odlaze\"",
      "url": "https://www.facebook.com/watch/?v=209334704509484",
      "date": "3 years ago",
      "date_raw": "3 years ago",
      "likes": 0,
      "comments": 0,
      "shares": 0,
      "views": "",
      "description": "",
      "thumbnail_url": ""
    },
    "1948379218664458": {
      "video_id": "1948379218664458",
      "title": "Draga mama 217.  \"Zagrli da prođe\"",
      "url": "https://www.facebook.com/watch/?v=1948379218664458",
      "date": "3 years ago",
      "date_raw": "3 years ago",
      "likes": 0,
      "comments": 0,
      "shares": 0,
      "views": "",
      "description": "",
      "thumbnail_url": ""
    },
    "296132782227011": {
      "video_id": "296132782227011",
      "title": "Draga mama 2016.  \"Dva načina\"",
      "url": "https://www.facebook.com/watch/?v=296132782227011",
      "date": "4 years ago",
      "date_raw": "4 years ago",
      "likes": 0,
      "comments": 0,
      "shares": 0,
      "views": "",
      "description": "",
      "thumbnail_url": ""
    },
    "199560968327405": {
      "video_id": "199560968327405",
      "title": "Draga mama 215. Online meeting and video conference",
      "url": "https://www.facebook.com/watch/?v=199560968327405",
      "date": "4 years ago",
      "date_raw": "4 years ago",
      "likes": 0,
      "comments": 0,
      "shares": 0,
      "views": "",
      "description": "",
      "thumbnail_url": ""
    },
    "731144567546827": {
      "video_id": "731144567546827",
      "title": "Draga mama 214. Dolasci i odlasci",
      "url": "https://www.facebook.com/watch/?v=731144567546827",
      "date": "4 years ago",
      "date_raw": "4 years ago",
      "likes": 0,
      "comments": 0,
      "shares": 0,
      "views": "",
      "description": "",
      "thumbnail_url": ""
    },
    "840752826770156": {
      "video_id": "840752826770156",
      "title": "Draga mama 213. Tamo gdje se poslovi, boje i igračke dijele na muške i ženske",
      "url": "https://www.facebook.com/watch/?v=840752826770156",
      "date": "4 years ago",
      "date_raw": "4 years ago",
      "likes": 0,
      "comments": 0,
      "shares": 0,
      "views": "",
      "description": "",
      "thumbnail_url": ""
    },
    "1047063372469521": {
      "video_id": "1047063372469521",
      "title": "Draga mama 212. Sretna nova godina",
      "url": "https://www.facebook.com/watch/?v=1047063372469521",
      "date": "4 years ago",
      "date_raw": "4 years ago",
      "likes": 0,
      "comments": 0,
      "shares": 0,
      "views": "",
      "description": "",
      "thumbnail_url": ""
    },
    "386743699272737": {
      "video_id": "386743699272737",
      "title": "Draga mama 211. izdanje",
      "url": "https://www.facebook.com/watch/?v=386743699272737",
      "date": "4 years ago",
      "date_raw": "4 years ago",
      "likes": 0,
      "comments": 0,
      "shares": 0,
      "views": "",
      "description": "",
      "thumbnail_url": ""
    },
    "799559127546890": {
      "video_id": "799559127546890",
      "title": "Draga mama 210.",
      "url": "https://www.facebook.com/watch/?v=799559127546890",
      "date": "4 years ago",
      "date_raw": "4 years ago",
      "likes": 0,
      "comments": 0,
      "shares": 0,
      "views": "",
      "description": "",
      "thumbnail_url": ""
    },
    "3353144248134418": {
      "video_id": "3353144248134418",
      "title": "Draga mama 209. \"Saliha Erika Glodar\"",
      "url": "https://www.facebook.com/watch/?v=3353144248134418",
      "date": "4 years ago",
      "date_raw": "4 years ago",
      "likes": 0,
      "comments": 0,
      "shares": 0,
      "views": "",
      "description": "",
      "thumbnail_url": ""
    },
    "394517285283903": {
      "video_id": "394517285283903",
      "title": "Draga mama 208. [Episode Title Unknown]",
      "url": "https://www.facebook.com/watch/?v=394517285283903",
      "date": "4 years ago",
      "date_raw": "4 years ago",
      "likes": 0,
      "comments": 0,
      "shares": 0,
      "views": "",
      "description": "",
      "thumbnail_url": ""
    },
    "2657564571170105": {
      "video_id": "2657564571170105",
      "title": "Draga mama 207. 'Eto čo'eka'",
      "url": "https://www.facebook.com/watch/?v=2657564571170105",
      "date": "4 years ago",
      "date_raw": "4 years ago",
      "likes": 0,
      "comments": 0,
      "shares": 0,
      "views": "",
      "description": "",
      "thumbnail_url": ""
    },
    "2748210275415322": {
      "video_id": "2748210275415322",
      "title": "Draga mama 206. \"Ono kad je Uzeir tješio Vericu\"",
      "url": "https://www.facebook.com/watch/?v=2748210275415322",
      "date": "4 years ago",
      "date_raw": "4 years ago",
      "likes": 0,
      "comments": 0,
      "shares": 0,
      "views": "",
      "description": "",
      "thumbnail_url": ""
    },
    "614060016193622": {
      "video_id": "614060016193622",
      "title": "Draga mama 205. Francesco José Riquelme",
      "url": "https://www.facebook.com/watch/?v=614060016193622",
      "date": "4 years ago",
      "date_raw": "4 years ago",
      "likes": 0,
      "comments": 0,
      "shares": 0,
      "views": "",
      "description": "",
      "thumbnail_url": ""
    },
    "692539514480490": {
      "video_id": "692539514480490",
      "title": "Draga mama 204. \"Draga mama\"",
      "url": "https://www.facebook.com/watch/?v=692539514480490",
      "date": "4 years ago",
      "date_raw": "4 years ago",
      "likes": 0,
      "comments": 0,
      "shares": 0,
      "views": "",
      "description": "",
      "thumbnail_url": ""
    },
    "804640990066431": {
      "video_id": "804640990066431",
      "title": "Draga mama 203. izdanje podnaziva \"Svi su isti, samo su neki istiji od drugih\"",
      "url": "https://www.facebook.com/watch/?v=804640990066431",
      "date": "5 years ago",
      "date_raw": "5 years ago",
      "likes": 0,
      "comments": 0,
      "shares": 0,
      "views": "",
      "description": "",
      "thumbnail_url": ""
    },
    "1143053939376616": {
      "video_id": "1143053939376616",
      "title": "Draga mama 202. Oswaldo je budan",
      "url": "https://www.facebook.com/watch/?v=1143053939376616",
      "date": "5 years ago",
      "date_raw": "5 years ago",
      "likes": 0,
      "comments": 0,
      "shares": 0,
      "views": "",
      "description": "",
      "thumbnail_url": ""
    },
    "565150284110464": {
      "video_id": "565150284110464",
      "title": "Draga mama 201. \"Kad si sretan ti zapucaj u zrak",
      "url": "https://www.facebook.com/watch/?v=565150284110464",
      "date": "5 years ago",
      "date_raw": "5 years ago",
      "likes": 0,
      "comments": 0,
      "shares": 0,
      "views": "",
      "description": "",
      "thumbnail_url": ""
    },
    "242191466951336": {
      "video_id": "242191466951336",
      "title": "Draga mama 200. Zvijer",
      "url": "https://www.facebook.com/watch/?v=242191466951336",
      "date": "5 years ago",
      "date_raw": "5 years ago",
      "likes": 0,
      "comments": 0,
      "shares": 0,
      "views": "",
      "description": "",
      "thumbnail_url": ""
    },
    "125583352142907": {
      "video_id": "125583352142907",
      "title": "Draga mama 199. [Episode Title Unknown]",
      "url": "https://www.facebook.com/watch/?v=125583352142907",
      "date": "5 years ago",
      "date_raw": "5 years ago",
      "likes": 0,
      "comments": 0,
      "shares": 0,
      "views": "",
      "description": "",
      "thumbnail_url": ""
    },
    "762167667614363": {
      "video_id": "762167667614363",
      "title": "Draga mama 198.  \"Jevrosim\"",
      "url": "https://www.facebook.com/watch/?v=762167667614363",
      "date": "5 years ago",
      "date_raw": "5 years ago",
      "likes": 0,
      "comments": 0,
      "shares": 0,
      "views": "",
      "description": "",
      "thumbnail_url": ""
    },
    "2499278853473742": {
      "video_id": "2499278853473742",
      "title": "Draga mama 197. 'Divan dan za biti ja'",
      "url": "https://www.facebook.com/watch/?v=2499278853473742",
      "date": "5 years ago",
      "date_raw": "5 years ago",
      "likes": 0,
      "comments": 0,
      "shares": 0,
      "views": "",
      "description": "",
      "thumbnail_url": ""
    },
    "485043108756397": {
      "video_id": "485043108756397",
      "title": "Draga mama 196. Cvijetko Osudić",
      "url": "https://www.facebook.com/watch/?v=485043108756397",
      "date": "5 years ago",
      "date_raw": "5 years ago",
      "likes": 0,
      "comments": 0,
      "shares": 0,
      "views": "",
      "description": "",
      "thumbnail_url": ""
    },
    "403156533679893": {
      "video_id": "403156533679893",
      "title": "Draga mama 195. Hilarijo i teleće oči",
      "url": "https://www.facebook.com/watch/?v=403156533679893",
      "date": "5 years ago",
      "date_raw": "5 years ago",
      "likes": 0,
      "comments": 0,
      "shares": 0,
      "views": "",
      "description": "",
      "thumbnail_url": ""
    },
    "2508315136054626": {
      "video_id": "2508315136054626",
      "title": "Draga mama 194. Jedan dan je jedan život",
      "url": "https://www.facebook.com/watch/?v=2508315136054626",
      "date": "5 years ago",
      "date_raw": "5 years ago",
      "likes": 0,
      "comments": 0,
      "shares": 0,
      "views": "",
      "description": "",
      "thumbnail_url": ""
    },
    "2321368628192076": {
      "video_id": "2321368628192076",
      "title": "Draga mama 193. Muriel i Farel",
      "url": "https://www.facebook.com/watch/?v=2321368628192076",
      "date": "5 years ago",
      "date_raw": "5 years ago",
      "likes": 0,
      "comments": 0,
      "shares": 0,
      "views": "",
      "description": "",
      "thumbnail_url": ""
    },
    "866500940379773": {
      "video_id": "866500940379773",
      "title": "Draga mama 192. Šta žulja Žulju",
      "url": "https://www.facebook.com/watch/?v=866500940379773",
      "date": "5 years ago",
      "date_raw": "5 years ago",
      "likes": 0,
      "comments": 0,
      "shares": 0,
      "views": "",
      "description": "",
      "thumbnail_url": ""
    },
    "2187878598191397": {
      "video_id": "2187878598191397",
      "title": "Draga mama 191. Čuda su moguća",
      "url": "https://www.facebook.com/watch/?v=2187878598191397",
      "date": "6 years ago",
      "date_raw": "6 years ago",
      "likes": 0,
      "comments": 0,
      "shares": 0,
      "views": "",
      "description": "",
      "thumbnail_url": ""
    },
    "497156197777790": {
      "video_id": "497156197777790",
      "title": "Draga mama 190. \"Draga mama\"",
      "url": "https://www.facebook.com/watch/?v=497156197777790",
      "date": "6 years ago",
      "date_raw": "6 years ago",
      "likes": 0,
      "comments": 0,
      "shares": 0,
      "views": "",
      "description": "",
      "thumbnail_url": ""
    },
    "277384933159168": {
      "video_id": "277384933159168",
      "title": "Draga mama 188. Rugao se ugao ruglu",
      "url": "https://www.facebook.com/watch/?v=277384933159168",
      "date": "6 years ago",
      "date_raw": "6 years ago",
      "likes": 0,
      "comments": 0,
      "shares": 0,
      "views": "",
      "description": "",
      "thumbnail_url": ""
    },
    "1140807289413503": {
      "video_id": "1140807289413503",
      "title": "Draga mama 187. Sve između",
      "url": "https://www.facebook.com/watch/?v=1140807289413503",
      "date": "6 years ago",
      "date_raw": "6 years ago",
      "likes": 0,
      "comments": 0,
      "shares": 0,
      "views": "",
      "description": "",
      "thumbnail_url": ""
    },
    "451159102082383": {
      "video_id": "451159102082383",
      "title": "Draga mama 185. Nahrani svoju glavu",
      "url": "https://www.facebook.com/watch/?v=451159102082383",
      "date": "6 years ago",
      "date_raw": "6 years ago",
      "likes": 0,
      "comments": 0,
      "shares": 0,
      "views": "",
      "description": "",
      "thumbnail_url": ""
    },
    "386800948527171": {
      "video_id": "386800948527171",
      "title": "Draga mama 184. Slika tebe o sebi",
      "url": "https://www.facebook.com/watch/?v=386800948527171",
      "date": "6 years ago",
      "date_raw": "6 years ago",
      "likes": 0,
      "comments": 0,
      "shares": 0,
      "views": "",
      "description": "",
      "thumbnail_url": ""
    },
    "2007744302856453": {
      "video_id": "2007744302856453",
      "title": "Draga mama 183. Život poslije fotografije",
      "url": "https://www.facebook.com/watch/?v=2007744302856453",
      "date": "6 years ago",
      "date_raw": "6 years ago",
      "likes": 0,
      "comments": 0,
      "shares": 0,
      "views": "",
      "description": "",
      "thumbnail_url": ""
    },
    "1207510889429039": {
      "video_id": "1207510889429039",
      "title": "Draga mama 182. Penal",
      "url": "https://www.facebook.com/watch/?v=1207510889429039",
      "date": "6 years ago",
      "date_raw": "6 years ago",
      "likes": 0,
      "comments": 0,
      "shares": 0,
      "views": "",
      "description": "",
      "thumbnail_url": ""
    },
    "2080097618973104": {
      "video_id": "2080097618973104",
      "title": "Draga mama 181. Lutkarstvo i rat kao startup",
      "url": "https://www.facebook.com/watch/?v=2080097618973104",
      "date": "6 years ago",
      "date_raw": "6 years ago",
      "likes": 0,
      "comments": 0,
      "shares": 0,
      "views": "",
      "description": "",
      "thumbnail_url": ""
    },
    "478875485958689": {
      "video_id": "478875485958689",
      "title": "Draga mama 180. Glasna tišina",
      "url": "https://www.facebook.com/watch/?v=478875485958689",
      "date": "6 years ago",
      "date_raw": "6 years ago",
      "likes": 0,
      "comments": 0,
      "shares": 0,
      "views": "",
      "description": "",
      "thumbnail_url": ""
    },
    "1042265105946101": {
      "video_id": "1042265105946101",
      "title": "Draga mama 179. Jednina u MI VI i ONI",
      "url": "https://www.facebook.com/watch/?v=1042265105946101",
      "date": "6 years ago",
      "date_raw": "6 years ago",
      "likes": 0,
      "comments": 0,
      "shares": 0,
      "views": "",
      "description": "",
      "thumbnail_url": ""
    },
    "413255085866670": {
      "video_id": "413255085866670",
      "title": "Draga mama 178. Strahovi pored puta",
      "url": "https://www.facebook.com/watch/?v=413255085866670",
      "date": "6 years ago",
      "date_raw": "6 years ago",
      "likes": 0,
      "comments": 0,
      "shares": 0,
      "views": "",
      "description": "",
      "thumbnail_url": ""
    },
    "1867704906620178": {
      "video_id": "1867704906620178",
      "title": "Draga mama 177. Buđenje",
      "url": "https://www.facebook.com/watch/?v=1867704906620178",
      "date": "6 years ago",
      "date_raw": "6 years ago",
      "likes": 0,
      "comments": 0,
      "shares": 0,
      "views": "",
      "description": "",
      "thumbnail_url": ""
    },
    "1792899137434089": {
      "video_id": "1792899137434089",
      "title": "Draga mama 176. Pravda za Davida",
      "url": "https://www.facebook.com/watch/?v=1792899137434089",
      "date": "7 years ago",
      "date_raw": "7 years ago",
      "likes": 0,
      "comments": 0,
      "shares": 0,
      "views": "",
      "description": "",
      "thumbnail_url": ""
    },
    "1777284602328876": {
      "video_id": "1777284602328876",
      "title": "Draga mama 175. Žive pare u mrtvom džepu",
      "url": "https://www.facebook.com/watch/?v=1777284602328876",
      "date": "7 years ago",
      "date_raw": "7 years ago",
      "likes": 0,
      "comments": 0,
      "shares": 0,
      "views": "",
      "description": "",
      "thumbnail_url": ""
    },
    "1758383594218977": {
      "video_id": "1758383594218977",
      "title": "Draga mama 174. Deep shit bro, deep shit",
      "url": "https://www.facebook.com/watch/?v=1758383594218977",
      "date": "7 years ago",
      "date_raw": "7 years ago",
      "likes": 0,
      "comments": 0,
      "shares": 0,
      "views": "",
      "description": "",
      "thumbnail_url": ""
    },
    "1719142778143059": {
      "video_id": "1719142778143059",
      "title": "Draga mama 173. Alvaro po zakonu",
      "url": "https://www.facebook.com/watch/?v=1719142778143059",
      "date": "7 years ago",
      "date_raw": "7 years ago",
      "likes": 0,
      "comments": 0,
      "shares": 0,
      "views": "",
      "description": "",
      "thumbnail_url": ""
    },
    "1690648027659201": {
      "video_id": "1690648027659201",
      "title": "Draga mama 172. Egobortus",
      "url": "https://www.facebook.com/watch/?v=1690648027659201",
      "date": "7 years ago",
      "date_raw": "7 years ago",
      "likes": 0,
      "comments": 0,
      "shares": 0,
      "views": "",
      "description": "",
      "thumbnail_url": ""
    },
    "1676005345790136": {
      "video_id": "1676005345790136",
      "title": "DM 171. Kriza, krizanteme i osmijeh u prolazu",
      "url": "https://www.facebook.com/watch/?v=1676005345790136",
      "date": "7 years ago",
      "date_raw": "7 years ago",
      "likes": 0,
      "comments": 0,
      "shares": 0,
      "views": "",
      "description": "",
      "thumbnail_url": ""
    },
    "1656186191105385": {
      "video_id": "1656186191105385",
      "title": "Draga mama 170. Probudi sebe prije tebe i budi tamo prije sebe",
      "url": "https://www.facebook.com/watch/?v=1656186191105385",
      "date": "7 years ago",
      "date_raw": "7 years ago",
      "likes": 0,
      "comments": 0,
      "shares": 0,
      "views": "",
      "description": "",
      "thumbnail_url": ""
    },
    "1641399945917343": {
      "video_id": "1641399945917343",
      "title": "Draga mama 167. Nek' je živa glava",
      "url": "https://www.facebook.com/watch/?v=1641399945917343",
      "date": "7 years ago",
      "date_raw": "7 years ago",
      "likes": 0,
      "comments": 0,
      "shares": 0,
      "views": "",
      "description": "",
      "thumbnail_url": ""
    },
    "1618793971511274": {
      "video_id": "1618793971511274",
      "title": "Draga mama 169. U haramu nema lijeka",
      "url": "https://www.facebook.com/watch/?v=1618793971511274",
      "date": "7 years ago",
      "date_raw": "7 years ago",
      "likes": 0,
      "comments": 0,
      "shares": 0,
      "views": "",
      "description": "",
      "thumbnail_url": ""
    },
    "1610812035642801": {
      "video_id": "1610812035642801",
      "title": "Draga mama 168. Mir",
      "url": "https://www.facebook.com/watch/?v=1610812035642801",
      "date": "7 years ago",
      "date_raw": "7 years ago",
      "likes": 0,
      "comments": 0,
      "shares": 0,
      "views": "",
      "description": "",
      "thumbnail_url": ""
    },
    "1579649468759058": {
      "video_id": "1579649468759058",
      "title": "Draga mama 166. Mozgov",
      "url": "https://www.facebook.com/watch/?v=1579649468759058",
      "date": "7 years ago",
      "date_raw": "7 years ago",
      "likes": 0,
      "comments": 0,
      "shares": 0,
      "views": "",
      "description": "",
      "thumbnail_url": ""
    },
    "1557392464318092": {
      "video_id": "1557392464318092",
      "title": "Draga mama 165. Buhenvald",
      "url": "https://www.facebook.com/watch/?v=1557392464318092",
      "date": "7 years ago",
      "date_raw": "7 years ago",
      "likes": 0,
      "comments": 0,
      "shares": 0,
      "views": "",
      "description": "",
      "thumbnail_url": ""
    },
    "1538488736208465": {
      "video_id": "1538488736208465",
      "title": "Draga mama 164. Bože i sirotinji si težak",
      "url": "https://www.facebook.com/watch/?v=1538488736208465",
      "date": "7 years ago",
      "date_raw": "7 years ago",
      "likes": 0,
      "comments": 0,
      "shares": 0,
      "views": "",
      "description": "",
      "thumbnail_url": ""
    },
    "1518432934880712": {
      "video_id": "1518432934880712",
      "title": "Draga mama 163. Jednim Havijerom na dvije stolice",
      "url": "https://www.facebook.com/watch/?v=1518432934880712",
      "date": "7 years ago",
      "date_raw": "7 years ago",
      "likes": 0,
      "comments": 0,
      "shares": 0,
      "views": "",
      "description": "",
      "thumbnail_url": ""
    },
    "1506598336064172": {
      "video_id": "1506598336064172",
      "title": "DRAGA MAMA, 162.",
      "url": "https://www.facebook.com/watch/?v=1506598336064172",
      "date": "7 years ago",
      "date_raw": "7 years ago",
      "likes": 0,
      "comments": 0,
      "shares": 0,
      "views": "",
      "description": "",
      "thumbnail_url": ""
    },
    "1496705510386788": {
      "video_id": "1496705510386788",
      "title": "Draga mama 160. [Episode Title Unknown]",
      "url": "https://www.facebook.com/watch/?v=1496705510386788",
      "date": "7 years ago",
      "date_raw": "7 years ago",
      "likes": 0,
      "comments": 0,
      "shares": 0,
      "views": "",
      "description": "",
      "thumbnail_url": ""
    },
    "1490775087646497": {
      "video_id": "1490775087646497",
      "title": "Draga mama 161. Kad ja pođem na radio i kad pođem u Budvu",
      "url": "https://www.facebook.com/watch/?v=1490775087646497",
      "date": "7 years ago",
      "date_raw": "7 years ago",
      "likes": 0,
      "comments": 0,
      "shares": 0,
      "views": "",
      "description": "",
      "thumbnail_url": ""
    },
    "1475743132483026": {
      "video_id": "1475743132483026",
      "title": "Draga mama 159. Lapodija",
      "url": "https://www.facebook.com/watch/?v=1475743132483026",
      "date": "7 years ago",
      "date_raw": "7 years ago",
      "likes": 0,
      "comments": 0,
      "shares": 0,
      "views": "",
      "description": "",
      "thumbnail_url": ""
    },
    "1455977097792963": {
      "video_id": "1455977097792963",
      "title": "Draga mama 160. Potok",
      "url": "https://www.facebook.com/watch/?v=1455977097792963",
      "date": "8 years ago",
      "date_raw": "8 years ago",
      "likes": 0,
      "comments": 0,
      "shares": 0,
      "views": "",
      "description": "",
      "thumbnail_url": ""
    },
    "1440617235995616": {
      "video_id": "1440617235995616",
      "title": "Draga mama 157. Gore",
      "url": "https://www.facebook.com/watch/?v=1440617235995616",
      "date": "8 years ago",
      "date_raw": "8 years ago",
      "likes": 0,
      "comments": 0,
      "shares": 0,
      "views": "",
      "description": "",
      "thumbnail_url": ""
    },
    "1424558337601506": {
      "video_id": "1424558337601506",
      "title": "Draga mama 158. Maca",
      "url": "https://www.facebook.com/watch/?v=1424558337601506",
      "date": "8 years ago",
      "date_raw": "8 years ago",
      "likes": 0,
      "comments": 0,
      "shares": 0,
      "views": "",
      "description": "",
      "thumbnail_url": ""
    },
    "1383598901697450": {
      "video_id": "1383598901697450",
      "title": "Draga mama 156. Tri četiri sad",
      "url": "https://www.facebook.com/watch/?v=1383598901697450",
      "date": "8 years ago",
      "date_raw": "8 years ago",
      "likes": 0,
      "comments": 0,
      "shares": 0,
      "views": "",
      "description": "",
      "thumbnail_url": ""
    },
    "1369210929802914": {
      "video_id": "1369210929802914",
      "title": "Draga mama 155. Kod Rozija",
      "url": "https://www.facebook.com/watch/?v=1369210929802914",
      "date": "8 years ago",
      "date_raw": "8 years ago",
      "likes": 0,
      "comments": 0,
      "shares": 0,
      "views": "",
      "description": "",
      "thumbnail_url": ""
    },
    "1353718308018843": {
      "video_id": "1353718308018843",
      "title": "Draga mama 154. Ništa lično",
      "url": "https://www.facebook.com/watch/?v=1353718308018843",
      "date": "8 years ago",
      "date_raw": "8 years ago",
      "likes": 0,
      "comments": 0,
      "shares": 0,
      "views": "",
      "description": "",
      "thumbnail_url": ""
    },
    "1336216973102310": {
      "video_id": "1336216973102310",
      "title": "Draga mama 153. Sa Buckom na ti",
      "url": "https://www.facebook.com/watch/?v=1336216973102310",
      "date": "8 years ago",
      "date_raw": "8 years ago",
      "likes": 0,
      "comments": 0,
      "shares": 0,
      "views": "",
      "description": "",
      "thumbnail_url": ""
    },
    "1313689148688426": {
      "video_id": "1313689148688426",
      "title": "Draga mama 151. Dismr ti čapri",
      "url": "https://www.facebook.com/watch/?v=1313689148688426",
      "date": "8 years ago",
      "date_raw": "8 years ago",
      "likes": 0,
      "comments": 0,
      "shares": 0,
      "views": "",
      "description": "",
      "thumbnail_url": ""
    },
    "1313686995355308": {
      "video_id": "1313686995355308",
      "title": "Draga mama 152. Greške našle mene",
      "url": "https://www.facebook.com/watch/?v=1313686995355308",
      "date": "8 years ago",
      "date_raw": "8 years ago",
      "likes": 0,
      "comments": 0,
      "shares": 0,
      "views": "",
      "description": "",
      "thumbnail_url": ""
    },
    "1287021881355153": {
      "video_id": "1287021881355153",
      "title": "Draga mama 150. Novogodišnja",
      "url": "https://www.facebook.com/watch/?v=1287021881355153",
      "date": "8 years ago",
      "date_raw": "8 years ago",
      "likes": 0,
      "comments": 0,
      "shares": 0,
      "views": "",
      "description": "",
      "thumbnail_url": ""
    },
    "1270903259633682": {
      "video_id": "1270903259633682",
      "title": "Draga mama 149. Murisa",
      "url": "https://www.facebook.com/watch/?v=1270903259633682",
      "date": "8 years ago",
      "date_raw": "8 years ago",
      "likes": 0,
      "comments": 0,
      "shares": 0,
      "views": "",
      "description": "",
      "thumbnail_url": ""
    },
    "1240987312625277": {
      "video_id": "1240987312625277",
      "title": "Draga mama 148. Integrativni koncept vladajuće vrhovne icjelju",
      "url": "https://www.facebook.com/watch/?v=1240987312625277",
      "date": "8 years ago",
      "date_raw": "8 years ago",
      "likes": 0,
      "comments": 0,
      "shares": 0,
      "views": "",
      "description": "",
      "thumbnail_url": ""
    },
    "1230908196966522": {
      "video_id": "1230908196966522",
      "title": "Draga mama 147. Svi ćemo",
      "url": "https://www.facebook.com/watch/?v=1230908196966522",
      "date": "8 years ago",
      "date_raw": "8 years ago",
      "likes": 0,
      "comments": 0,
      "shares": 0,
      "views": "",
      "description": "",
      "thumbnail_url": ""
    },
    "1210517255672283": {
      "video_id": "1210517255672283",
      "title": "Draga mama 144. \"Cvaja\"",
      "url": "https://www.facebook.com/watch/?v=1210517255672283",
      "date": "8 years ago",
      "date_raw": "8 years ago",
      "likes": 0,
      "comments": 0,
      "shares": 0,
      "views": "",
      "description": "",
      "thumbnail_url": ""
    },
    "1201009103289765": {
      "video_id": "1201009103289765",
      "title": "Draga mama 146. Želja s četiri lista",
      "url": "https://www.facebook.com/watch/?v=1201009103289765",
      "date": "8 years ago",
      "date_raw": "8 years ago",
      "likes": 0,
      "comments": 0,
      "shares": 0,
      "views": "",
      "description": "",
      "thumbnail_url": ""
    },
    "1187611014629574": {
      "video_id": "1187611014629574",
      "title": "DRAGAMAMA_Video_1187611014629574",
      "url": "https://www.facebook.com/watch/?v=1187611014629574",
      "date": "",
      "date_raw": "",
      "likes": 0,
      "comments": 0,
      "shares": 0,
      "views": "",
      "description": "",
      "thumbnail_url": ""
    },
    "1183863321671010": {
      "video_id": "1183863321671010",
      "title": "Draga mama 143. Interpretacijska neistina",
      "url": "https://www.facebook.com/watch/?v=1183863321671010",
      "date": "8 years ago",
      "date_raw": "8 years ago",
      "likes": 0,
      "comments": 0,
      "shares": 0,
      "views": "",
      "description": "",
      "thumbnail_url": ""
    },
    "1169671416423534": {
      "video_id": "1169671416423534",
      "title": "Draga mama 142. Asifa",
      "url": "https://www.facebook.com/watch/?v=1169671416423534",
      "date": "8 years ago",
      "date_raw": "8 years ago",
      "likes": 0,
      "comments": 0,
      "shares": 0,
      "views": "",
      "description": "",
      "thumbnail_url": ""
    },
    "1141285455928797": {
      "video_id": "1141285455928797",
      "title": "Draga mama 141. Klop(k)a",
      "url": "https://www.facebook.com/watch/?v=1141285455928797",
      "date": "8 years ago",
      "date_raw": "8 years ago",
      "likes": 0,
      "comments": 0,
      "shares": 0,
      "views": "",
      "description": "",
      "thumbnail_url": ""
    },
    "1132586836798659": {
      "video_id": "1132586836798659",
      "title": "Draga mama 140. EXIT i Novi Sad",
      "url": "https://www.facebook.com/watch/?v=1132586836798659",
      "date": "8 years ago",
      "date_raw": "8 years ago",
      "likes": 0,
      "comments": 0,
      "shares": 0,
      "views": "",
      "description": "",
      "thumbnail_url": ""
    },
    "1111538612236815": {
      "video_id": "1111538612236815",
      "title": "Draga mama 139. Puno rupa",
      "url": "https://www.facebook.com/watch/?v=1111538612236815",
      "date": "9 years ago",
      "date_raw": "9 years ago",
      "likes": 0,
      "comments": 0,
      "shares": 0,
      "views": "",
      "description": "",
      "thumbnail_url": ""
    },
    "1105471482843528": {
      "video_id": "1105471482843528",
      "title": "DRAGAMAMA_Video_1105471482843528",
      "url": "https://www.facebook.com/watch/?v=1105471482843528",
      "date": "",
      "date_raw": "",
      "likes": 0,
      "comments": 0,
      "shares": 0,
      "views": "",
      "description": "",
      "thumbnail_url": ""
    },
    "1094396480617695": {
      "video_id": "1094396480617695",
      "title": "Draga mama 137. Baš k'o Halid",
      "url": "https://www.facebook.com/watch/?v=1094396480617695",
      "date": "9 years ago",
      "date_raw": "9 years ago",
      "likes": 0,
      "comments": 0,
      "shares": 0,
      "views": "",
      "description": "",
      "thumbnail_url": ""
    },
    "1084131528310857": {
      "video_id": "1084131528310857",
      "title": "Draga mama 136. Skotrljano govno",
      "url": "https://www.facebook.com/watch/?v=1084131528310857",
      "date": "9 years ago",
      "date_raw": "9 years ago",
      "likes": 0,
      "comments": 0,
      "shares": 0,
      "views": "",
      "description": "",
      "thumbnail_url": ""
    },
    "1078427505547926": {
      "video_id": "1078427505547926",
      "title": "Draga mama 135. Pizza s majonezom",
      "url": "https://www.facebook.com/watch/?v=1078427505547926",
      "date": "9 years ago",
      "date_raw": "9 years ago",
      "likes": 0,
      "comments": 0,
      "shares": 0,
      "views": "",
      "description": "",
      "thumbnail_url": ""
    },
    "1061195863937757": {
      "video_id": "1061195863937757",
      "title": "Draga mama 134. \"Draga mama - Konkurs\"",
      "url": "https://www.facebook.com/watch/?v=1061195863937757",
      "date": "9 years ago",
      "date_raw": "9 years ago",
      "likes": 0,
      "comments": 0,
      "shares": 0,
      "views": "",
      "description": "",
      "thumbnail_url": ""
    },
    "1039067206150623": {
      "video_id": "1039067206150623",
      "title": "Draga mama 131. Dobar je i Bog",
      "url": "https://www.facebook.com/watch/?v=1039067206150623",
      "date": "9 years ago",
      "date_raw": "9 years ago",
      "likes": 0,
      "comments": 0,
      "shares": 0,
      "views": "",
      "description": "",
      "thumbnail_url": ""
    },
    "1022093517847992": {
      "video_id": "1022093517847992",
      "title": "Draga mama 129. Evolucija",
      "url": "https://www.facebook.com/watch/?v=1022093517847992",
      "date": "9 years ago",
      "date_raw": "9 years ago",
      "likes": 0,
      "comments": 0,
      "shares": 0,
      "views": "",
      "description": "",
      "thumbnail_url": ""
    },
    "1003967939660550": {
      "video_id": "1003967939660550",
      "title": "Draga mama 128. - Sretna nova godina",
      "url": "https://www.facebook.com/watch/?v=1003967939660550",
      "date": "9 years ago",
      "date_raw": "9 years ago",
      "likes": 0,
      "comments": 0,
      "shares": 0,
      "views": "",
      "description": "",
      "thumbnail_url": ""
    },
    "1001824803208197": {
      "video_id": "1001824803208197",
      "title": "Draga mama 127. Za neutralne",
      "url": "https://www.facebook.com/watch/?v=1001824803208197",
      "date": "9 years ago",
      "date_raw": "9 years ago",
      "likes": 0,
      "comments": 0,
      "shares": 0,
      "views": "",
      "description": "",
      "thumbnail_url": ""
    },
    "998970573493620": {
      "video_id": "998970573493620",
      "title": "Draga mama 126.  \"Navikli na navike\"",
      "url": "https://www.facebook.com/watch/?v=998970573493620",
      "date": "9 years ago",
      "date_raw": "9 years ago",
      "likes": 0,
      "comments": 0,
      "shares": 0,
      "views": "",
      "description": "",
      "thumbnail_url": ""
    },
    "987358687988142": {
      "video_id": "987358687988142",
      "title": "Draga mama 125. [Episode Title Unknown]",
      "url": "https://www.facebook.com/watch/?v=987358687988142",
      "date": "9 years ago",
      "date_raw": "9 years ago",
      "likes": 0,
      "comments": 0,
      "shares": 0,
      "views": "",
      "description": "",
      "thumbnail_url": ""
    },
    "978133958910615": {
      "video_id": "978133958910615",
      "title": "Draga mama 124. - Potraga ubija samu sebe",
      "url": "https://www.facebook.com/watch/?v=978133958910615",
      "date": "9 years ago",
      "date_raw": "9 years ago",
      "likes": 0,
      "comments": 0,
      "shares": 0,
      "views": "",
      "description": "",
      "thumbnail_url": ""
    },
    "963992706991407": {
      "video_id": "963992706991407",
      "title": "Draga mama 123. - Đes' ti bio '92",
      "url": "https://www.facebook.com/watch/?v=963992706991407",
      "date": "9 years ago",
      "date_raw": "9 years ago",
      "likes": 0,
      "comments": 0,
      "shares": 0,
      "views": "",
      "description": "",
      "thumbnail_url": ""
    },
    "958876234169721": {
      "video_id": "958876234169721",
      "title": "Draga mama 122. - Gdje sam rođen tu je sve životinja",
      "url": "https://www.facebook.com/watch/?v=958876234169721",
      "date": "9 years ago",
      "date_raw": "9 years ago",
      "likes": 0,
      "comments": 0,
      "shares": 0,
      "views": "",
      "description": "",
      "thumbnail_url": ""
    },
    "949858878404790": {
      "video_id": "949858878404790",
      "title": "Draga mama 121. - Zidovi, izbjeglice i apokalipsa",
      "url": "https://www.facebook.com/watch/?v=949858878404790",
      "date": "9 years ago",
      "date_raw": "9 years ago",
      "likes": 0,
      "comments": 0,
      "shares": 0,
      "views": "",
      "description": "",
      "thumbnail_url": ""
    },
    "946185218772156": {
      "video_id": "946185218772156",
      "title": "Draga mama 120. Za Mirjanu",
      "url": "https://www.facebook.com/watch/?v=946185218772156",
      "date": "9 years ago",
      "date_raw": "9 years ago",
      "likes": 0,
      "comments": 0,
      "shares": 0,
      "views": "",
      "description": "",
      "thumbnail_url": ""
    },
    "935500056507339": {
      "video_id": "935500056507339",
      "title": "Draga mama 119. Srdele na gradele",
      "url": "https://www.facebook.com/watch/?v=935500056507339",
      "date": "9 years ago",
      "date_raw": "9 years ago",
      "likes": 0,
      "comments": 0,
      "shares": 0,
      "views": "",
      "description": "",
      "thumbnail_url": ""
    },
    "924637687593576": {
      "video_id": "924637687593576",
      "title": "Draga mama 118. Vuk u Ezopskoj Uniji",
      "url": "https://www.facebook.com/watch/?v=924637687593576",
      "date": "9 years ago",
      "date_raw": "9 years ago",
      "likes": 0,
      "comments": 0,
      "shares": 0,
      "views": "",
      "description": "",
      "thumbnail_url": ""
    },
    "922137451176933": {
      "video_id": "922137451176933",
      "title": "Draga mama 117. - Metropole od pekare pa do rane zore",
      "url": "https://www.facebook.com/watch/?v=922137451176933",
      "date": "9 years ago",
      "date_raw": "9 years ago",
      "likes": 0,
      "comments": 0,
      "shares": 0,
      "views": "",
      "description": "",
      "thumbnail_url": ""
    },
    "910539935670018": {
      "video_id": "910539935670018",
      "title": "Draga mama 116. Hindustan Motors",
      "url": "https://www.facebook.com/watch/?v=910539935670018",
      "date": "10 years ago",
      "date_raw": "10 years ago",
      "likes": 0,
      "comments": 0,
      "shares": 0,
      "views": "",
      "description": "",
      "thumbnail_url": ""
    },
    "903423286381683": {
      "video_id": "903423286381683",
      "title": "Draga mama 115. - Kiselost",
      "url": "https://www.facebook.com/watch/?v=903423286381683",
      "date": "10 years ago",
      "date_raw": "10 years ago",
      "likes": 0,
      "comments": 0,
      "shares": 0,
      "views": "",
      "description": "",
      "thumbnail_url": ""
    },
    "891648187559193": {
      "video_id": "891648187559193",
      "title": "Draga mama 114: ''Prođi, neće ti Roki ništa''",
      "url": "https://www.facebook.com/watch/?v=891648187559193",
      "date": "10 years ago",
      "date_raw": "10 years ago",
      "likes": 0,
      "comments": 0,
      "shares": 0,
      "views": "",
      "description": "",
      "thumbnail_url": ""
    },
    "887312354659443": {
      "video_id": "887312354659443",
      "title": "Draga mama 113. Nek' je čista slika",
      "url": "https://www.facebook.com/watch/?v=887312354659443",
      "date": "10 years ago",
      "date_raw": "10 years ago",
      "likes": 0,
      "comments": 0,
      "shares": 0,
      "views": "",
      "description": "",
      "thumbnail_url": ""
    },
    "880889321968413": {
      "video_id": "880889321968413",
      "title": "Draga mama 112. - Jedno te isto",
      "url": "https://www.facebook.com/watch/?v=880889321968413",
      "date": "10 years ago",
      "date_raw": "10 years ago",
      "likes": 0,
      "comments": 0,
      "shares": 0,
      "views": "",
      "description": "",
      "thumbnail_url": ""
    },
    "876616192395726": {
      "video_id": "876616192395726",
      "title": "Draga mama 111. - Karcinomska logika",
      "url": "https://www.facebook.com/watch/?v=876616192395726",
      "date": "10 years ago",
      "date_raw": "10 years ago",
      "likes": 0,
      "comments": 0,
      "shares": 0,
      "views": "",
      "description": "",
      "thumbnail_url": ""
    },
    "860174144039931": {
      "video_id": "860174144039931",
      "title": "Draga mama 110. - Posljedice nisu uzroci",
      "url": "https://www.facebook.com/watch/?v=860174144039931",
      "date": "10 years ago",
      "date_raw": "10 years ago",
      "likes": 0,
      "comments": 0,
      "shares": 0,
      "views": "",
      "description": "",
      "thumbnail_url": ""
    },
    "858783464178999": {
      "video_id": "858783464178999",
      "title": "Draga mama 109. - Uvod u život",
      "url": "https://www.facebook.com/watch/?v=858783464178999",
      "date": "10 years ago",
      "date_raw": "10 years ago",
      "likes": 0,
      "comments": 0,
      "shares": 0,
      "views": "",
      "description": "",
      "thumbnail_url": ""
    },
    "854118414645504": {
      "video_id": "854118414645504",
      "title": "DRAGAMAMA_Video_854118414645504",
      "url": "https://www.facebook.com/watch/?v=854118414645504",
      "date": "",
      "date_raw": "",
      "likes": 0,
      "comments": 0,
      "shares": 0,
      "views": "",
      "description": "",
      "thumbnail_url": ""
    },
    "842539989136680": {
      "video_id": "842539989136680",
      "title": "Draga mama 108. Labilizam",
      "url": "https://www.facebook.com/watch/?v=842539989136680",
      "date": "10 years ago",
      "date_raw": "10 years ago",
      "likes": 0,
      "comments": 0,
      "shares": 0,
      "views": "",
      "description": "",
      "thumbnail_url": ""
    },
    "834716119919067": {
      "video_id": "834716119919067",
      "title": "Draga mama 107. - Da sam ja netko",
      "url": "https://www.facebook.com/watch/?v=834716119919067",
      "date": "10 years ago",
      "date_raw": "10 years ago",
      "likes": 0,
      "comments": 0,
      "shares": 0,
      "views": "",
      "description": "",
      "thumbnail_url": ""
    },
    "825123860878293": {
      "video_id": "825123860878293",
      "title": "Draga mama 106. \"Plaćaš da se ne sjećaš\"",
      "url": "https://www.facebook.com/watch/?v=825123860878293",
      "date": "10 years ago",
      "date_raw": "10 years ago",
      "likes": 0,
      "comments": 0,
      "shares": 0,
      "views": "",
      "description": "",
      "thumbnail_url": ""
    },
    "818399078217438": {
      "video_id": "818399078217438",
      "title": "DRAGAMAMA_Video_818399078217438",
      "url": "https://www.facebook.com/watch/?v=818399078217438",
      "date": "",
      "date_raw": "",
      "likes": 0,
      "comments": 0,
      "shares": 0,
      "views": "",
      "description": "",
      "thumbnail_url": ""
    },
    "807587359298610": {
      "video_id": "807587359298610",
      "title": "Draga mama 105. - Pogled iz ptičje perspektive",
      "url": "https://www.facebook.com/watch/?v=807587359298610",
      "date": "10 years ago",
      "date_raw": "10 years ago",
      "likes": 0,
      "comments": 0,
      "shares": 0,
      "views": "",
      "description": "",
      "thumbnail_url": ""
    },
    "805100889547257": {
      "video_id": "805100889547257",
      "title": "DRAGAMAMA_Video_805100889547257",
      "url": "https://www.facebook.com/watch/?v=805100889547257",
      "date": "",
      "date_raw": "",
      "likes": 0,
      "comments": 0,
      "shares": 0,
      "views": "",
      "description": "",
      "thumbnail_url": ""
    },
    "799975623393117": {
      "video_id": "799975623393117",
      "title": "DRAGAMAMA_Video_799975623393117",
      "url": "https://www.facebook.com/watch/?v=799975623393117",
      "date": "",
      "date_raw": "",
      "likes": 0,
      "comments": 0,
      "shares": 0,
      "views": "",
      "description": "",
      "thumbnail_url": ""
    },
    "795773710479975": {
      "video_id": "795773710479975",
      "title": "Draga mama 104. Pozitivnostavljanje pozitivnog stava",
      "url": "https://www.facebook.com/watch/?v=795773710479975",
      "date": "10 years ago",
      "date_raw": "10 years ago",
      "likes": 0,
      "comments": 0,
      "shares": 0,
      "views": "",
      "description": "",
      "thumbnail_url": ""
    },
    "793922913998388": {
      "video_id": "793922913998388",
      "title": "Draga mama 103. - Usisivač",
      "url": "https://www.facebook.com/watch/?v=793922913998388",
      "date": "10 years ago",
      "date_raw": "10 years ago",
      "likes": 0,
      "comments": 0,
      "shares": 0,
      "views": "",
      "description": "",
      "thumbnail_url": ""
    },
    "789631007760912": {
      "video_id": "789631007760912",
      "title": "DRAGAMAMA_Video_789631007760912",
      "url": "https://www.facebook.com/watch/?v=789631007760912",
      "date": "",
      "date_raw": "",
      "likes": 0,
      "comments": 0,
      "shares": 0,
      "views": "",
      "description": "",
      "thumbnail_url": ""
    },
    "781500058574007": {
      "video_id": "781500058574007",
      "title": "Draga mama 102. - In memoriam D",
      "url": "https://www.facebook.com/watch/?v=781500058574007",
      "date": "10 years ago",
      "date_raw": "10 years ago",
      "likes": 0,
      "comments": 0,
      "shares": 0,
      "views": "",
      "description": "",
      "thumbnail_url": ""
    },
    "776822175708462": {
      "video_id": "776822175708462",
      "title": "Draga mama 101. - Izaberi jedan broj, sigurno ćeš pogriješiti",
      "url": "https://www.facebook.com/watch/?v=776822175708462",
      "date": "10 years ago",
      "date_raw": "10 years ago",
      "likes": 0,
      "comments": 0,
      "shares": 0,
      "views": "",
      "description": "",
      "thumbnail_url": ""
    },
    "773639766026703": {
      "video_id": "773639766026703",
      "title": "DRAGAMAMA_Video_773639766026703",
      "url": "https://www.facebook.com/watch/?v=773639766026703",
      "date": "",
      "date_raw": "",
      "likes": 0,
      "comments": 0,
      "shares": 0,
      "views": "",
      "description": "",
      "thumbnail_url": ""
    },
    "766379470086066": {
      "video_id": "766379470086066",
      "title": "DRAGAMAMA_Video_766379470086066",
      "url": "https://www.facebook.com/watch/?v=766379470086066",
      "date": "",
      "date_raw": "",
      "likes": 0,
      "comments": 0,
      "shares": 0,
      "views": "",
      "description": "",
      "thumbnail_url": ""
    },
    "764607293596617": {
      "video_id": "764607293596617",
      "title": "DRAGAMAMA_Video_764607293596617",
      "url": "https://www.facebook.com/watch/?v=764607293596617",
      "date": "",
      "date_raw": "",
      "likes": 0,
      "comments": 0,
      "shares": 0,
      "views": "",
      "description": "",
      "thumbnail_url": ""
    },
    "758642697526410": {
      "video_id": "758642697526410",
      "title": "DRAGAMAMA_Video_758642697526410",
      "url": "https://www.facebook.com/watch/?v=758642697526410",
      "date": "",
      "date_raw": "",
      "likes": 0,
      "comments": 0,
      "shares": 0,
      "views": "",
      "description": "",
      "thumbnail_url": ""
    },
    "755603301163683": {
      "video_id": "755603301163683",
      "title": "DRAGAMAMA_Video_755603301163683",
      "url": "https://www.facebook.com/watch/?v=755603301163683",
      "date": "",
      "date_raw": "",
      "likes": 0,
      "comments": 0,
      "shares": 0,
      "views": "",
      "description": "",
      "thumbnail_url": ""
    },
    "751074788283201": {
      "video_id": "751074788283201",
      "title": "DRAGAMAMA_Video_751074788283201",
      "url": "https://www.facebook.com/watch/?v=751074788283201",
      "date": "",
      "date_raw": "",
      "likes": 0,
      "comments": 0,
      "shares": 0,
      "views": "",
      "description": "",
      "thumbnail_url": ""
    },
    "748291258561554": {
      "video_id": "748291258561554",
      "title": "Draga mama 97. Sanjin zaista postoji",
      "url": "https://www.facebook.com/watch/?v=748291258561554",
      "date": "10 years ago",
      "date_raw": "10 years ago",
      "likes": 0,
      "comments": 0,
      "shares": 0,
      "views": "",
      "description": "",
      "thumbnail_url": ""
    },
    "747843348606345": {
      "video_id": "747843348606345",
      "title": "DRAGAMAMA_Video_747843348606345",
      "url": "https://www.facebook.com/watch/?v=747843348606345",
      "date": "",
      "date_raw": "",
      "likes": 0,
      "comments": 0,
      "shares": 0,
      "views": "",
      "description": "",
      "thumbnail_url": ""
    },
    "741938842530129": {
      "video_id": "741938842530129",
      "title": "DRAGAMAMA_Video_741938842530129",
      "url": "https://www.facebook.com/watch/?v=741938842530129",
      "date": "",
      "date_raw": "",
      "likes": 0,
      "comments": 0,
      "shares": 0,
      "views": "",
      "description": "",
      "thumbnail_url": ""
    },
    "738070216250325": {
      "video_id": "738070216250325",
      "title": "Draga mama 64. - Guslar i Skalar",
      "url": "https://www.facebook.com/watch/?v=738070216250325",
      "date": "10 years ago",
      "date_raw": "10 years ago",
      "likes": 0,
      "comments": 0,
      "shares": 0,
      "views": "",
      "description": "",
      "thumbnail_url": ""
    },
    "731205443603469": {
      "video_id": "731205443603469",
      "title": "Draga mama 94. Hostel Racional",
      "url": "https://www.facebook.com/watch/?v=731205443603469",
      "date": "10 years ago",
      "date_raw": "10 years ago",
      "likes": 0,
      "comments": 0,
      "shares": 0,
      "views": "",
      "description": "",
      "thumbnail_url": ""
    },
    "727986467258700": {
      "video_id": "727986467258700",
      "title": "DRAGAMAMA_Video_727986467258700",
      "url": "https://www.facebook.com/watch/?v=727986467258700",
      "date": "",
      "date_raw": "",
      "likes": 0,
      "comments": 0,
      "shares": 0,
      "views": "",
      "description": "",
      "thumbnail_url": ""
    },
    "723327011057979": {
      "video_id": "723327011057979",
      "title": "DRAGAMAMA_Video_723327011057979",
      "url": "https://www.facebook.com/watch/?v=723327011057979",
      "date": "",
      "date_raw": "",
      "likes": 0,
      "comments": 0,
      "shares": 0,
      "views": "",
      "description": "",
      "thumbnail_url": ""
    },
    "714475748609772": {
      "video_id": "714475748609772",
      "title": "DRAGAMAMA_Video_714475748609772",
      "url": "https://www.facebook.com/watch/?v=714475748609772",
      "date": "11 years ago",
      "date_raw": "11 years ago",
      "likes": 0,
      "comments": 0,
      "shares": 0,
      "views": "",
      "description": "",
      "thumbnail_url": ""
    },
    "710851268972220": {
      "video_id": "710851268972220",
      "title": "DRAGAMAMA_Video_710851268972220",
      "url": "https://www.facebook.com/watch/?v=710851268972220",
      "date": "",
      "date_raw": "",
      "likes": 0,
      "comments": 0,
      "shares": 0,
      "views": "",
      "description": "",
      "thumbnail_url": ""
    },
    "708782925845721": {
      "video_id": "708782925845721",
      "title": "DRAGAMAMA_Video_708782925845721",
      "url": "https://www.facebook.com/watch/?v=708782925845721",
      "date": "",
      "date_raw": "",
      "likes": 0,
      "comments": 0,
      "shares": 0,
      "views": "",
      "description": "",
      "thumbnail_url": ""
    },
    "698260716897942": {
      "video_id": "698260716897942",
      "title": "Draga mama. \"Gigane pobratime mio...\"",
      "url": "https://www.facebook.com/watch/?v=698260716897942",
      "date": "11 years ago",
      "date_raw": "11 years ago",
      "likes": 0,
      "comments": 0,
      "shares": 0,
      "views": "",
      "description": "",
      "thumbnail_url": ""
    },
    "693151210742226": {
      "video_id": "693151210742226",
      "title": "DRAGAMAMA_Video_693151210742226",
      "url": "https://www.facebook.com/watch/?v=693151210742226",
      "date": "",
      "date_raw": "",
      "likes": 0,
      "comments": 0,
      "shares": 0,
      "views": "",
      "description": "",
      "thumbnail_url": ""
    },
    "687524387971575": {
      "video_id": "687524387971575",
      "title": "DRAGAMAMA_Video_687524387971575",
      "url": "https://www.facebook.com/watch/?v=687524387971575",
      "date": "",
      "date_raw": "",
      "likes": 0,
      "comments": 0,
      "shares": 0,
      "views": "",
      "description": "",
      "thumbnail_url": ""
    },
    "682053758518638": {
      "video_id": "682053758518638",
      "title": "DRAGAMAMA_Video_682053758518638",
      "url": "https://www.facebook.com/watch/?v=682053758518638",
      "date": "",
      "date_raw": "",
      "likes": 0,
      "comments": 0,
      "shares": 0,
      "views": "",
      "description": "",
      "thumbnail_url": ""
    },
    "676983585692322": {
      "video_id": "676983585692322",
      "title": "DRAGAMAMA_Video_676983585692322",
      "url": "https://www.facebook.com/watch/?v=676983585692322",
      "date": "",
      "date_raw": "",
      "likes": 0,
      "comments": 0,
      "shares": 0,
      "views": "",
      "description": "",
      "thumbnail_url": ""
    },
    "674129355977745": {
      "video_id": "674129355977745",
      "title": "DRAGAMAMA_Video_674129355977745",
      "url": "https://www.facebook.com/watch/?v=674129355977745",
      "date": "",
      "date_raw": "",
      "likes": 0,
      "comments": 0,
      "shares": 0,
      "views": "",
      "description": "",
      "thumbnail_url": ""
    },
    "672832909440723": {
      "video_id": "672832909440723",
      "title": "DRAGAMAMA_Video_672832909440723",
      "url": "https://www.facebook.com/watch/?v=672832909440723",
      "date": "",
      "date_raw": "",
      "likes": 0,
      "comments": 0,
      "shares": 0,
      "views": "",
      "description": "",
      "thumbnail_url": ""
    },
    "669493406441340": {
      "video_id": "669493406441340",
      "title": "DRAGAMAMA_Video_669493406441340",
      "url": "https://www.facebook.com/watch/?v=669493406441340",
      "date": "11 years ago",
      "date_raw": "11 years ago",
      "likes": 0,
      "comments": 0,
      "shares": 0,
      "views": "",
      "description": "",
      "thumbnail_url": ""
    },
    "664935286897152": {
      "video_id": "664935286897152",
      "title": "DRAGAMAMA_Video_664935286897152",
      "url": "https://www.facebook.com/watch/?v=664935286897152",
      "date": "",
      "date_raw": "",
      "likes": 0,
      "comments": 0,
      "shares": 0,
      "views": "",
      "description": "",
      "thumbnail_url": ""
    },
    "656644967726184": {
      "video_id": "656644967726184",
      "title": "DRAGAMAMA_Video_656644967726184",
      "url": "https://www.facebook.com/watch/?v=656644967726184",
      "date": "",
      "date_raw": "",
      "likes": 0,
      "comments": 0,
      "shares": 0,
      "views": "",
      "description": "",
      "thumbnail_url": ""
    },
    "635919113132103": {
      "video_id": "635919113132103",
      "title": "DRAGAMAMA_Video_635919113132103",
      "url": "https://www.facebook.com/watch/?v=635919113132103",
      "date": "",
      "date_raw": "",
      "likes": 0,
      "comments": 0,
      "shares": 0,
      "views": "",
      "description": "",
      "thumbnail_url": ""
    },
    "635917029798978": {
      "video_id": "635917029798978",
      "title": "DRAGAMAMA_Video_635917029798978",
      "url": "https://www.facebook.com/watch/?v=635917029798978",
      "date": "",
      "date_raw": "",
      "likes": 0,
      "comments": 0,
      "shares": 0,
      "views": "",
      "description": "",
      "thumbnail_url": ""
    },
    "635915366465811": {
      "video_id": "635915366465811",
      "title": "Draga mama 81. Življe groblje i PRINT SCRN",
      "url": "https://www.facebook.com/watch/?v=635915366465811",
      "date": "11 years ago",
      "date_raw": "11 years ago",
      "likes": 0,
      "comments": 0,
      "shares": 0,
      "views": "",
      "description": "",
      "thumbnail_url": ""
    },
    "635914739799207": {
      "video_id": "635914739799207",
      "title": "DRAGAMAMA_Video_635914739799207",
      "url": "https://www.facebook.com/watch/?v=635914739799207",
      "date": "",
      "date_raw": "",
      "likes": 0,
      "comments": 0,
      "shares": 0,
      "views": "",
      "description": "",
      "thumbnail_url": ""
    },
    "635914023132612": {
      "video_id": "635914023132612",
      "title": "DRAGAMAMA_Video_635914023132612",
      "url": "https://www.facebook.com/watch/?v=635914023132612",
      "date": "",
      "date_raw": "",
      "likes": 0,
      "comments": 0,
      "shares": 0,
      "views": "",
      "description": "",
      "thumbnail_url": ""
    },
    "10201500151657676": {
      "video_id": "10201500151657676",
      "title": "DRAGAMAMA_Video_10201500151657676",
      "url": "https://www.facebook.com/watch/?v=10201500151657676",
      "date": "",
      "date_raw": "",
      "likes": 0,
      "comments": 0,
      "shares": 0,
      "views": "",
      "description": "",
      "thumbnail_url": ""
    },
    "10201500133937233": {
      "video_id": "10201500133937233",
      "title": "DRAGAMAMA_Video_10201500133937233",
      "url": "https://www.facebook.com/watch/?v=10201500133937233",
      "date": "",
      "date_raw": "",
      "likes": 0,
      "comments": 0,
      "shares": 0,
      "views": "",
      "description": "",
      "thumbnail_url": ""
    },
    "10201500089536123": {
      "video_id": "10201500089536123",
      "title": "Draga mama 75. Bitno je piti Konjak",
      "url": "https://www.facebook.com/watch/?v=10201500089536123",
      "date": "11 years ago",
      "date_raw": "11 years ago",
      "likes": 0,
      "comments": 0,
      "shares": 0,
      "views": "",
      "description": "",
      "thumbnail_url": ""
    }
  },
  "total_sessions": 11,
  "total_videos": 1315,
  "unique_videos": 156,
  "total_time": 1142.2975800037384,
  "total_score": 186099,
  "best_session_score": 42313
}